psytrace/__init__.py
psytrace-0.0.1.dist-info/METADATA
psytrace-0.0.1.dist-info/WHEEL
psytrace-0.0.1.dist-info/top_level.txt
psytrace-0.0.1.dist-info/RECORD
