Metadata-Version: 2.4
Name: psytrace
Version: 0.0.1
Summary: A tool for psychological traces
Author-email: "Michael J. Lee" <mil@mit.edu>
License: MIT
Requires-Python: >=3.11
